<?xml version="1.0" encoding="UTF-8"?>

<object classname="com.jeta.forms.store.memento.FormPackage">
 <at name="fileversion">
  <object classname="com.jeta.forms.store.memento.FormsVersion2">
   <at name="major">2</at>
   <at name="minor">0</at>
   <at name="sub">0</at>
  </object>
 </at>
 <at name="form">
  <object classname="com.jeta.forms.store.memento.FormMemento">
   <super classname="com.jeta.forms.store.memento.ComponentMemento">
    <at name="cellconstraints">
     <object classname="com.jeta.forms.store.memento.CellConstraintsMemento">
      <at name="column">1</at>
      <at name="row">1</at>
      <at name="colspan">1</at>
      <at name="rowspan">1</at>
      <at name="halign">default</at>
      <at name="valign">default</at>
      <at name="insets" object="insets">0,0,0,0</at>
     </object>
    </at>
    <at name="componentclass">com.jeta.forms.gui.form.FormComponent</at>
   </super>
   <at name="id">/Users/hydrologis/development/hortonmachine-git/apps/src/main/java/org/hortonmachine/gforms/FormBuilderView.xml</at>
   <at name="rowspecs">CENTER:DEFAULT:NONE,CENTER:DEFAULT:NONE,CENTER:DEFAULT:NONE,CENTER:DEFAULT:NONE,CENTER:DEFAULT:NONE,CENTER:DEFAULT:NONE,CENTER:DEFAULT:NONE,CENTER:DEFAULT:NONE,CENTER:DEFAULT:NONE,CENTER:DEFAULT:NONE,CENTER:DEFAULT:NONE,CENTER:DEFAULT:GROW(1.0),CENTER:DEFAULT:NONE,CENTER:DEFAULT:NONE,CENTER:DEFAULT:NONE,CENTER:DEFAULT:NONE,CENTER:DEFAULT:NONE,CENTER:DEFAULT:NONE,CENTER:DEFAULT:NONE,CENTER:DEFAULT:NONE,CENTER:DEFAULT:NONE,CENTER:DEFAULT:NONE</at>
   <at name="colspecs">FILL:DEFAULT:NONE,FILL:DEFAULT:NONE,FILL:DEFAULT:NONE,FILL:DEFAULT:NONE,FILL:DEFAULT:GROW(1.0),FILL:DEFAULT:NONE,FILL:DEFAULT:NONE,FILL:DEFAULT:NONE,FILL:DEFAULT:NONE,FILL:DEFAULT:NONE,FILL:DEFAULT:NONE,FILL:DEFAULT:NONE,FILL:DEFAULT:NONE,FILL:DEFAULT:NONE,FILL:DEFAULT:NONE,FILL:DEFAULT:NONE,FILL:DEFAULT:NONE,FILL:DEFAULT:NONE,FILL:DEFAULT:NONE,FILL:DEFAULT:NONE</at>
   <at name="components">
    <object classname="java.util.LinkedList">
     <item >
      <at name="value">
       <object classname="com.jeta.forms.store.memento.BeanMemento">
        <super classname="com.jeta.forms.store.memento.ComponentMemento">
         <at name="cellconstraints">
          <object classname="com.jeta.forms.store.memento.CellConstraintsMemento">
           <at name="column">2</at>
           <at name="row">2</at>
           <at name="colspan">14</at>
           <at name="rowspan">1</at>
           <at name="halign">default</at>
           <at name="valign">default</at>
           <at name="insets" object="insets">0,0,0,0</at>
          </object>
         </at>
         <at name="componentclass">com.jeta.forms.gui.form.StandardComponent</at>
        </super>
        <at name="jetabeanclass">com.jeta.forms.gui.beans.JETABean</at>
        <at name="beanclass">javax.swing.JTextField</at>
        <at name="beanproperties">
         <object classname="com.jeta.forms.store.memento.PropertiesMemento">
          <at name="classname">javax.swing.JTextField</at>
          <at name="properties">
           <object classname="com.jeta.forms.store.support.PropertyMap">
            <at name="border">
             <object classname="com.jeta.forms.store.properties.CompoundBorderProperty">
              <super classname="com.jeta.forms.store.properties.BorderProperty">
               <at name="name">border</at>
              </super>
              <at name="borders">
               <object classname="java.util.LinkedList">
                <item >
                 <at name="value">
                  <object classname="com.jeta.forms.store.properties.DefaultBorderProperty">
                   <super classname="com.jeta.forms.store.properties.BorderProperty">
                    <at name="name">border</at>
                   </super>
                  </object>
                 </at>
                </item>
               </object>
              </at>
             </object>
            </at>
            <at name="name">filePathtext</at>
            <at name="width">668</at>
            <at name="height">26</at>
           </object>
          </at>
         </object>
        </at>
       </object>
      </at>
     </item>
     <item >
      <at name="value">
       <object classname="com.jeta.forms.store.memento.BeanMemento">
        <super classname="com.jeta.forms.store.memento.ComponentMemento">
         <at name="cellconstraints">
          <object classname="com.jeta.forms.store.memento.CellConstraintsMemento">
           <at name="column">17</at>
           <at name="row">2</at>
           <at name="colspan">1</at>
           <at name="rowspan">1</at>
           <at name="halign">default</at>
           <at name="valign">default</at>
           <at name="insets" object="insets">0,0,0,0</at>
          </object>
         </at>
         <at name="componentclass">com.jeta.forms.gui.form.StandardComponent</at>
        </super>
        <at name="jetabeanclass">com.jeta.forms.gui.beans.JETABean</at>
        <at name="beanclass">javax.swing.JButton</at>
        <at name="beanproperties">
         <object classname="com.jeta.forms.store.memento.PropertiesMemento">
          <at name="classname">javax.swing.JButton</at>
          <at name="properties">
           <object classname="com.jeta.forms.store.support.PropertyMap">
            <at name="border">
             <object classname="com.jeta.forms.store.properties.CompoundBorderProperty">
              <super classname="com.jeta.forms.store.properties.BorderProperty">
               <at name="name">border</at>
              </super>
              <at name="borders">
               <object classname="java.util.LinkedList">
                <item >
                 <at name="value">
                  <object classname="com.jeta.forms.store.properties.DefaultBorderProperty">
                   <super classname="com.jeta.forms.store.properties.BorderProperty">
                    <at name="name">border</at>
                   </super>
                  </object>
                 </at>
                </item>
               </object>
              </at>
             </object>
            </at>
            <at name="actionCommand">...</at>
            <at name="name">browseButton</at>
            <at name="width">75</at>
            <at name="text">...</at>
            <at name="toolTipText">Load an existing Geopaparazzi Form</at>
            <at name="height">29</at>
           </object>
          </at>
         </object>
        </at>
       </object>
      </at>
     </item>
     <item >
      <at name="value">
       <object classname="com.jeta.forms.store.memento.BeanMemento">
        <super classname="com.jeta.forms.store.memento.ComponentMemento">
         <at name="cellconstraints">
          <object classname="com.jeta.forms.store.memento.CellConstraintsMemento">
           <at name="column">19</at>
           <at name="row">2</at>
           <at name="colspan">1</at>
           <at name="rowspan">1</at>
           <at name="halign">default</at>
           <at name="valign">default</at>
           <at name="insets" object="insets">0,0,0,0</at>
          </object>
         </at>
         <at name="componentclass">com.jeta.forms.gui.form.StandardComponent</at>
        </super>
        <at name="jetabeanclass">com.jeta.forms.gui.beans.JETABean</at>
        <at name="beanclass">javax.swing.JButton</at>
        <at name="beanproperties">
         <object classname="com.jeta.forms.store.memento.PropertiesMemento">
          <at name="classname">javax.swing.JButton</at>
          <at name="properties">
           <object classname="com.jeta.forms.store.support.PropertyMap">
            <at name="border">
             <object classname="com.jeta.forms.store.properties.CompoundBorderProperty">
              <super classname="com.jeta.forms.store.properties.BorderProperty">
               <at name="name">border</at>
              </super>
              <at name="borders">
               <object classname="java.util.LinkedList">
                <item >
                 <at name="value">
                  <object classname="com.jeta.forms.store.properties.DefaultBorderProperty">
                   <super classname="com.jeta.forms.store.properties.BorderProperty">
                    <at name="name">border</at>
                   </super>
                  </object>
                 </at>
                </item>
               </object>
              </at>
             </object>
            </at>
            <at name="actionCommand">new</at>
            <at name="name">newButton</at>
            <at name="width">75</at>
            <at name="text">new</at>
            <at name="toolTipText">Create a new Geopaparazzi Form</at>
            <at name="height">29</at>
           </object>
          </at>
         </object>
        </at>
       </object>
      </at>
     </item>
     <item >
      <at name="value">
       <object classname="com.jeta.forms.store.memento.BeanMemento">
        <super classname="com.jeta.forms.store.memento.ComponentMemento">
         <at name="cellconstraints">
          <object classname="com.jeta.forms.store.memento.CellConstraintsMemento">
           <at name="column">2</at>
           <at name="row">4</at>
           <at name="colspan">14</at>
           <at name="rowspan">1</at>
           <at name="halign">default</at>
           <at name="valign">default</at>
           <at name="insets" object="insets">0,0,0,0</at>
          </object>
         </at>
         <at name="componentclass">com.jeta.forms.gui.form.StandardComponent</at>
        </super>
        <at name="jetabeanclass">com.jeta.forms.gui.beans.JETABean</at>
        <at name="beanclass">javax.swing.JComboBox</at>
        <at name="beanproperties">
         <object classname="com.jeta.forms.store.memento.PropertiesMemento">
          <at name="classname">javax.swing.JComboBox</at>
          <at name="properties">
           <object classname="com.jeta.forms.store.support.PropertyMap">
            <at name="border">
             <object classname="com.jeta.forms.store.properties.CompoundBorderProperty">
              <super classname="com.jeta.forms.store.properties.BorderProperty">
               <at name="name">border</at>
              </super>
              <at name="borders">
               <object classname="java.util.LinkedList">
                <item >
                 <at name="value">
                  <object classname="com.jeta.forms.store.properties.DefaultBorderProperty">
                   <super classname="com.jeta.forms.store.properties.BorderProperty">
                    <at name="name">border</at>
                   </super>
                  </object>
                 </at>
                </item>
               </object>
              </at>
             </object>
            </at>
            <at name="name">buttonsCombo</at>
            <at name="width">668</at>
            <at name="items">
             <object classname="com.jeta.forms.store.properties.ItemsProperty">
              <at name="name">items</at>
             </object>
            </at>
            <at name="height">27</at>
           </object>
          </at>
         </object>
        </at>
       </object>
      </at>
     </item>
     <item >
      <at name="value">
       <object classname="com.jeta.forms.store.memento.BeanMemento">
        <super classname="com.jeta.forms.store.memento.ComponentMemento">
         <at name="cellconstraints">
          <object classname="com.jeta.forms.store.memento.CellConstraintsMemento">
           <at name="column">17</at>
           <at name="row">4</at>
           <at name="colspan">1</at>
           <at name="rowspan">1</at>
           <at name="halign">default</at>
           <at name="valign">default</at>
           <at name="insets" object="insets">0,0,0,0</at>
          </object>
         </at>
         <at name="componentclass">com.jeta.forms.gui.form.StandardComponent</at>
        </super>
        <at name="jetabeanclass">com.jeta.forms.gui.beans.JETABean</at>
        <at name="beanclass">javax.swing.JButton</at>
        <at name="beanproperties">
         <object classname="com.jeta.forms.store.memento.PropertiesMemento">
          <at name="classname">javax.swing.JButton</at>
          <at name="properties">
           <object classname="com.jeta.forms.store.support.PropertyMap">
            <at name="border">
             <object classname="com.jeta.forms.store.properties.CompoundBorderProperty">
              <super classname="com.jeta.forms.store.properties.BorderProperty">
               <at name="name">border</at>
              </super>
              <at name="borders">
               <object classname="java.util.LinkedList">
                <item >
                 <at name="value">
                  <object classname="com.jeta.forms.store.properties.DefaultBorderProperty">
                   <super classname="com.jeta.forms.store.properties.BorderProperty">
                    <at name="name">border</at>
                   </super>
                  </object>
                 </at>
                </item>
               </object>
              </at>
             </object>
            </at>
            <at name="actionCommand">add</at>
            <at name="name">addSectionButton</at>
            <at name="width">75</at>
            <at name="text">add</at>
            <at name="toolTipText">Add new Section (Geopaparazzi Button)</at>
            <at name="height">29</at>
           </object>
          </at>
         </object>
        </at>
       </object>
      </at>
     </item>
     <item >
      <at name="value">
       <object classname="com.jeta.forms.store.memento.BeanMemento">
        <super classname="com.jeta.forms.store.memento.ComponentMemento">
         <at name="cellconstraints">
          <object classname="com.jeta.forms.store.memento.CellConstraintsMemento">
           <at name="column">19</at>
           <at name="row">4</at>
           <at name="colspan">1</at>
           <at name="rowspan">1</at>
           <at name="halign">default</at>
           <at name="valign">default</at>
           <at name="insets" object="insets">0,0,0,0</at>
          </object>
         </at>
         <at name="componentclass">com.jeta.forms.gui.form.StandardComponent</at>
        </super>
        <at name="jetabeanclass">com.jeta.forms.gui.beans.JETABean</at>
        <at name="beanclass">javax.swing.JButton</at>
        <at name="beanproperties">
         <object classname="com.jeta.forms.store.memento.PropertiesMemento">
          <at name="classname">javax.swing.JButton</at>
          <at name="properties">
           <object classname="com.jeta.forms.store.support.PropertyMap">
            <at name="border">
             <object classname="com.jeta.forms.store.properties.CompoundBorderProperty">
              <super classname="com.jeta.forms.store.properties.BorderProperty">
               <at name="name">border</at>
              </super>
              <at name="borders">
               <object classname="java.util.LinkedList">
                <item >
                 <at name="value">
                  <object classname="com.jeta.forms.store.properties.DefaultBorderProperty">
                   <super classname="com.jeta.forms.store.properties.BorderProperty">
                    <at name="name">border</at>
                   </super>
                  </object>
                 </at>
                </item>
               </object>
              </at>
             </object>
            </at>
            <at name="actionCommand">del</at>
            <at name="name">deleteSectionButton</at>
            <at name="width">75</at>
            <at name="text">del</at>
            <at name="toolTipText">Delete selected Section  (Geopaparazzi Button)</at>
            <at name="height">29</at>
           </object>
          </at>
         </object>
        </at>
       </object>
      </at>
     </item>
     <item >
      <at name="value">
       <object classname="com.jeta.forms.store.memento.FormMemento">
        <super classname="com.jeta.forms.store.memento.ComponentMemento">
         <at name="cellconstraints">
          <object classname="com.jeta.forms.store.memento.CellConstraintsMemento">
           <at name="column">2</at>
           <at name="row">6</at>
           <at name="colspan">18</at>
           <at name="rowspan">16</at>
           <at name="halign">default</at>
           <at name="valign">default</at>
           <at name="insets" object="insets">0,0,0,0</at>
          </object>
         </at>
         <at name="componentclass">com.jeta.forms.gui.form.FormComponent</at>
        </super>
        <at name="id">embedded.1333012659</at>
        <at name="rowspecs">FILL:DEFAULT:GROW(1.0),CENTER:DEFAULT:NONE,CENTER:DEFAULT:NONE,CENTER:DEFAULT:NONE,CENTER:2DLU:NONE,CENTER:2DLU:NONE,CENTER:DEFAULT:NONE</at>
        <at name="colspecs">FILL:DEFAULT:GROW(1.0),FILL:DEFAULT:NONE</at>
        <at name="components">
         <object classname="java.util.LinkedList">
          <item >
           <at name="value">
            <object classname="com.jeta.forms.store.memento.FormMemento">
             <super classname="com.jeta.forms.store.memento.ComponentMemento">
              <at name="cellconstraints">
               <object classname="com.jeta.forms.store.memento.CellConstraintsMemento">
                <at name="column">1</at>
                <at name="row">7</at>
                <at name="colspan">1</at>
                <at name="rowspan">1</at>
                <at name="halign">default</at>
                <at name="valign">default</at>
                <at name="insets" object="insets">0,0,0,0</at>
               </object>
              </at>
              <at name="componentclass">com.jeta.forms.gui.form.FormComponent</at>
             </super>
             <at name="id">embedded.1163303699</at>
             <at name="rowspecs">CENTER:DEFAULT:NONE</at>
             <at name="colspecs">FILL:100DLU:NONE,FILL:4DLU:NONE,FILL:DEFAULT:NONE,FILL:30DLU:NONE,FILL:100DLU:NONE,FILL:4DLU:NONE,FILL:DEFAULT:NONE</at>
             <at name="components">
              <object classname="java.util.LinkedList">
               <item >
                <at name="value">
                 <object classname="com.jeta.forms.store.memento.BeanMemento">
                  <super classname="com.jeta.forms.store.memento.ComponentMemento">
                   <at name="cellconstraints">
                    <object classname="com.jeta.forms.store.memento.CellConstraintsMemento">
                     <at name="column">3</at>
                     <at name="row">1</at>
                     <at name="colspan">1</at>
                     <at name="rowspan">1</at>
                     <at name="halign">default</at>
                     <at name="valign">default</at>
                     <at name="insets" object="insets">0,0,0,0</at>
                    </object>
                   </at>
                   <at name="componentclass">com.jeta.forms.gui.form.StandardComponent</at>
                  </super>
                  <at name="jetabeanclass">com.jeta.forms.gui.beans.JETABean</at>
                  <at name="beanclass">javax.swing.JButton</at>
                  <at name="beanproperties">
                   <object classname="com.jeta.forms.store.memento.PropertiesMemento">
                    <at name="classname">javax.swing.JButton</at>
                    <at name="properties">
                     <object classname="com.jeta.forms.store.support.PropertyMap">
                      <at name="border">
                       <object classname="com.jeta.forms.store.properties.CompoundBorderProperty">
                        <super classname="com.jeta.forms.store.properties.BorderProperty">
                         <at name="name">border</at>
                        </super>
                        <at name="borders">
                         <object classname="java.util.LinkedList">
                          <item >
                           <at name="value">
                            <object classname="com.jeta.forms.store.properties.DefaultBorderProperty">
                             <super classname="com.jeta.forms.store.properties.BorderProperty">
                              <at name="name">border</at>
                             </super>
                            </object>
                           </at>
                          </item>
                         </object>
                        </at>
                       </object>
                      </at>
                      <at name="actionCommand">add</at>
                      <at name="name">addWidgetButton</at>
                      <at name="width">75</at>
                      <at name="text">add</at>
                      <at name="toolTipText">Add a selected widget to the current tab</at>
                      <at name="height">29</at>
                     </object>
                    </at>
                   </object>
                  </at>
                 </object>
                </at>
               </item>
               <item >
                <at name="value">
                 <object classname="com.jeta.forms.store.memento.BeanMemento">
                  <super classname="com.jeta.forms.store.memento.ComponentMemento">
                   <at name="cellconstraints">
                    <object classname="com.jeta.forms.store.memento.CellConstraintsMemento">
                     <at name="column">7</at>
                     <at name="row">1</at>
                     <at name="colspan">1</at>
                     <at name="rowspan">1</at>
                     <at name="halign">default</at>
                     <at name="valign">default</at>
                     <at name="insets" object="insets">0,0,0,0</at>
                    </object>
                   </at>
                   <at name="componentclass">com.jeta.forms.gui.form.StandardComponent</at>
                  </super>
                  <at name="jetabeanclass">com.jeta.forms.gui.beans.JETABean</at>
                  <at name="beanclass">javax.swing.JButton</at>
                  <at name="beanproperties">
                   <object classname="com.jeta.forms.store.memento.PropertiesMemento">
                    <at name="classname">javax.swing.JButton</at>
                    <at name="properties">
                     <object classname="com.jeta.forms.store.support.PropertyMap">
                      <at name="border">
                       <object classname="com.jeta.forms.store.properties.CompoundBorderProperty">
                        <super classname="com.jeta.forms.store.properties.BorderProperty">
                         <at name="name">border</at>
                        </super>
                        <at name="borders">
                         <object classname="java.util.LinkedList">
                          <item >
                           <at name="value">
                            <object classname="com.jeta.forms.store.properties.DefaultBorderProperty">
                             <super classname="com.jeta.forms.store.properties.BorderProperty">
                              <at name="name">border</at>
                             </super>
                            </object>
                           </at>
                          </item>
                         </object>
                        </at>
                       </object>
                      </at>
                      <at name="actionCommand">del</at>
                      <at name="name">deleteWidgetButton</at>
                      <at name="width">75</at>
                      <at name="text">del</at>
                      <at name="toolTipText">Delete selected widget from the current tab</at>
                      <at name="height">29</at>
                     </object>
                    </at>
                   </object>
                  </at>
                 </object>
                </at>
               </item>
               <item >
                <at name="value">
                 <object classname="com.jeta.forms.store.memento.BeanMemento">
                  <super classname="com.jeta.forms.store.memento.ComponentMemento">
                   <at name="cellconstraints">
                    <object classname="com.jeta.forms.store.memento.CellConstraintsMemento">
                     <at name="column">1</at>
                     <at name="row">1</at>
                     <at name="colspan">1</at>
                     <at name="rowspan">1</at>
                     <at name="halign">default</at>
                     <at name="valign">default</at>
                     <at name="insets" object="insets">0,0,0,0</at>
                    </object>
                   </at>
                   <at name="componentclass">com.jeta.forms.gui.form.StandardComponent</at>
                  </super>
                  <at name="jetabeanclass">com.jeta.forms.gui.beans.JETABean</at>
                  <at name="beanclass">javax.swing.JComboBox</at>
                  <at name="beanproperties">
                   <object classname="com.jeta.forms.store.memento.PropertiesMemento">
                    <at name="classname">javax.swing.JComboBox</at>
                    <at name="properties">
                     <object classname="com.jeta.forms.store.support.PropertyMap">
                      <at name="border">
                       <object classname="com.jeta.forms.store.properties.CompoundBorderProperty">
                        <super classname="com.jeta.forms.store.properties.BorderProperty">
                         <at name="name">border</at>
                        </super>
                        <at name="borders">
                         <object classname="java.util.LinkedList">
                          <item >
                           <at name="value">
                            <object classname="com.jeta.forms.store.properties.DefaultBorderProperty">
                             <super classname="com.jeta.forms.store.properties.BorderProperty">
                              <at name="name">border</at>
                             </super>
                            </object>
                           </at>
                          </item>
                         </object>
                        </at>
                       </object>
                      </at>
                      <at name="name">widgetsCombo</at>
                      <at name="width">188</at>
                      <at name="items">
                       <object classname="com.jeta.forms.store.properties.ItemsProperty">
                        <at name="name">items</at>
                       </object>
                      </at>
                      <at name="toolTipText">List of available widgets to add to the current tab.</at>
                      <at name="height">27</at>
                     </object>
                    </at>
                   </object>
                  </at>
                 </object>
                </at>
               </item>
               <item >
                <at name="value">
                 <object classname="com.jeta.forms.store.memento.BeanMemento">
                  <super classname="com.jeta.forms.store.memento.ComponentMemento">
                   <at name="cellconstraints">
                    <object classname="com.jeta.forms.store.memento.CellConstraintsMemento">
                     <at name="column">5</at>
                     <at name="row">1</at>
                     <at name="colspan">1</at>
                     <at name="rowspan">1</at>
                     <at name="halign">default</at>
                     <at name="valign">default</at>
                     <at name="insets" object="insets">0,0,0,0</at>
                    </object>
                   </at>
                   <at name="componentclass">com.jeta.forms.gui.form.StandardComponent</at>
                  </super>
                  <at name="jetabeanclass">com.jeta.forms.gui.beans.JETABean</at>
                  <at name="beanclass">javax.swing.JComboBox</at>
                  <at name="beanproperties">
                   <object classname="com.jeta.forms.store.memento.PropertiesMemento">
                    <at name="classname">javax.swing.JComboBox</at>
                    <at name="properties">
                     <object classname="com.jeta.forms.store.support.PropertyMap">
                      <at name="border">
                       <object classname="com.jeta.forms.store.properties.CompoundBorderProperty">
                        <super classname="com.jeta.forms.store.properties.BorderProperty">
                         <at name="name">border</at>
                        </super>
                        <at name="borders">
                         <object classname="java.util.LinkedList">
                          <item >
                           <at name="value">
                            <object classname="com.jeta.forms.store.properties.DefaultBorderProperty">
                             <super classname="com.jeta.forms.store.properties.BorderProperty">
                              <at name="name">border</at>
                             </super>
                            </object>
                           </at>
                          </item>
                         </object>
                        </at>
                       </object>
                      </at>
                      <at name="name">loadedWidgetsCombo</at>
                      <at name="width">188</at>
                      <at name="items">
                       <object classname="com.jeta.forms.store.properties.ItemsProperty">
                        <at name="name">items</at>
                       </object>
                      </at>
                      <at name="toolTipText">List of widgets on the current tab that can be removed.</at>
                      <at name="height">27</at>
                     </object>
                    </at>
                   </object>
                  </at>
                 </object>
                </at>
               </item>
              </object>
             </at>
             <at name="properties">
              <object classname="com.jeta.forms.store.memento.PropertiesMemento">
               <at name="classname">com.jeta.forms.gui.form.GridView</at>
               <at name="properties">
                <object classname="com.jeta.forms.store.support.PropertyMap">
                 <at name="border">
                  <object classname="com.jeta.forms.store.properties.CompoundBorderProperty">
                   <super classname="com.jeta.forms.store.properties.BorderProperty">
                    <at name="name">border</at>
                   </super>
                   <at name="borders">
                    <object classname="java.util.LinkedList"/>
                   </at>
                  </object>
                 </at>
                 <at name="name"/>
                 <at name="fill">
                  <object classname="com.jeta.forms.store.properties.effects.PaintProperty">
                   <at name="name">fill</at>
                  </object>
                 </at>
                 <at name="scollBars">
                  <object classname="com.jeta.forms.store.properties.ScrollBarsProperty">
                   <at name="name">scollBars</at>
                   <at name="verticalpolicy">21</at>
                   <at name="horizontalpolicy">31</at>
                   <at name="border">
                    <object classname="com.jeta.forms.store.properties.CompoundBorderProperty">
                     <super classname="com.jeta.forms.store.properties.BorderProperty">
                      <at name="name">border</at>
                     </super>
                     <at name="borders">
                      <object classname="java.util.LinkedList">
                       <item >
                        <at name="value">
                         <object classname="com.jeta.forms.store.properties.DefaultBorderProperty">
                          <super classname="com.jeta.forms.store.properties.BorderProperty">
                           <at name="name">border</at>
                          </super>
                         </object>
                        </at>
                       </item>
                      </object>
                     </at>
                    </object>
                   </at>
                  </object>
                 </at>
                </object>
               </at>
              </object>
             </at>
             <at name="cellpainters">
              <object classname="com.jeta.forms.store.support.Matrix">
               <at name="rows">
                <object classname="[Ljava.lang.Object;" size="1">
                 <at name="item" index="0">
                  <object classname="[Ljava.lang.Object;" size="7"/>
                 </at>
                </object>
               </at>
              </object>
             </at>
             <at name="rowgroups">
              <object classname="com.jeta.forms.store.memento.FormGroupSet">
               <at name="groups">
                <object classname="java.util.HashMap"/>
               </at>
              </object>
             </at>
             <at name="colgroups">
              <object classname="com.jeta.forms.store.memento.FormGroupSet">
               <at name="groups">
                <object classname="java.util.HashMap"/>
               </at>
              </object>
             </at>
            </object>
           </at>
          </item>
          <item >
           <at name="value">
            <object classname="com.jeta.forms.store.memento.BeanMemento">
             <super classname="com.jeta.forms.store.memento.ComponentMemento">
              <at name="cellconstraints">
               <object classname="com.jeta.forms.store.memento.CellConstraintsMemento">
                <at name="column">1</at>
                <at name="row">1</at>
                <at name="colspan">1</at>
                <at name="rowspan">5</at>
                <at name="halign">default</at>
                <at name="valign">default</at>
                <at name="insets" object="insets">0,0,0,0</at>
               </object>
              </at>
              <at name="componentclass">com.jeta.forms.gui.form.FormContainerComponent</at>
             </super>
             <at name="jetabeanclass">com.jeta.forms.gui.beans.JETABean</at>
             <at name="beanclass">javax.swing.JTabbedPane</at>
             <at name="beanproperties">
              <object classname="com.jeta.forms.store.memento.PropertiesMemento">
               <at name="classname">javax.swing.JTabbedPane</at>
               <at name="properties">
                <object classname="com.jeta.forms.store.support.PropertyMap">
                 <at name="border">
                  <object classname="com.jeta.forms.store.properties.CompoundBorderProperty">
                   <super classname="com.jeta.forms.store.properties.BorderProperty">
                    <at name="name">border</at>
                   </super>
                   <at name="borders">
                    <object classname="java.util.LinkedList">
                     <item >
                      <at name="value">
                       <object classname="com.jeta.forms.store.properties.DefaultBorderProperty">
                        <super classname="com.jeta.forms.store.properties.BorderProperty">
                         <at name="name">border</at>
                        </super>
                       </object>
                      </at>
                     </item>
                    </object>
                   </at>
                  </object>
                 </at>
                 <at name="tabPlacement">2</at>
                 <at name="tabLayoutPolicy">1</at>
                 <at name="name">buttonsTabPane</at>
                 <at name="tabs">
                  <object classname="com.jeta.forms.store.properties.TabbedPaneProperties">
                   <at name="name">tabs</at>
                   <at name="items">
                    <object classname="java.util.LinkedList"/>
                   </at>
                  </object>
                 </at>
                 <at name="width">774</at>
                 <at name="height">324</at>
                </object>
               </at>
              </object>
             </at>
            </object>
           </at>
          </item>
          <item >
           <at name="value">
            <object classname="com.jeta.forms.store.memento.BeanMemento">
             <super classname="com.jeta.forms.store.memento.ComponentMemento">
              <at name="cellconstraints">
               <object classname="com.jeta.forms.store.memento.CellConstraintsMemento">
                <at name="column">2</at>
                <at name="row">2</at>
                <at name="colspan">1</at>
                <at name="rowspan">1</at>
                <at name="halign">default</at>
                <at name="valign">default</at>
                <at name="insets" object="insets">0,0,0,0</at>
               </object>
              </at>
              <at name="componentclass">com.jeta.forms.gui.form.StandardComponent</at>
             </super>
             <at name="jetabeanclass">com.jeta.forms.gui.beans.JETABean</at>
             <at name="beanclass">javax.swing.JButton</at>
             <at name="beanproperties">
              <object classname="com.jeta.forms.store.memento.PropertiesMemento">
               <at name="classname">javax.swing.JButton</at>
               <at name="properties">
                <object classname="com.jeta.forms.store.support.PropertyMap">
                 <at name="border">
                  <object classname="com.jeta.forms.store.properties.CompoundBorderProperty">
                   <super classname="com.jeta.forms.store.properties.BorderProperty">
                    <at name="name">border</at>
                   </super>
                   <at name="borders">
                    <object classname="java.util.LinkedList">
                     <item >
                      <at name="value">
                       <object classname="com.jeta.forms.store.properties.DefaultBorderProperty">
                        <super classname="com.jeta.forms.store.properties.BorderProperty">
                         <at name="name">border</at>
                        </super>
                       </object>
                      </at>
                     </item>
                    </object>
                   </at>
                  </object>
                 </at>
                 <at name="actionCommand">add</at>
                 <at name="name">addFormButton</at>
                 <at name="width">75</at>
                 <at name="text">add</at>
                 <at name="toolTipText">Add new tab to the current section.</at>
                 <at name="height">29</at>
                </object>
               </at>
              </object>
             </at>
            </object>
           </at>
          </item>
          <item >
           <at name="value">
            <object classname="com.jeta.forms.store.memento.BeanMemento">
             <super classname="com.jeta.forms.store.memento.ComponentMemento">
              <at name="cellconstraints">
               <object classname="com.jeta.forms.store.memento.CellConstraintsMemento">
                <at name="column">2</at>
                <at name="row">4</at>
                <at name="colspan">1</at>
                <at name="rowspan">1</at>
                <at name="halign">default</at>
                <at name="valign">default</at>
                <at name="insets" object="insets">0,0,0,0</at>
               </object>
              </at>
              <at name="componentclass">com.jeta.forms.gui.form.StandardComponent</at>
             </super>
             <at name="jetabeanclass">com.jeta.forms.gui.beans.JETABean</at>
             <at name="beanclass">javax.swing.JButton</at>
             <at name="beanproperties">
              <object classname="com.jeta.forms.store.memento.PropertiesMemento">
               <at name="classname">javax.swing.JButton</at>
               <at name="properties">
                <object classname="com.jeta.forms.store.support.PropertyMap">
                 <at name="border">
                  <object classname="com.jeta.forms.store.properties.CompoundBorderProperty">
                   <super classname="com.jeta.forms.store.properties.BorderProperty">
                    <at name="name">border</at>
                   </super>
                   <at name="borders">
                    <object classname="java.util.LinkedList">
                     <item >
                      <at name="value">
                       <object classname="com.jeta.forms.store.properties.DefaultBorderProperty">
                        <super classname="com.jeta.forms.store.properties.BorderProperty">
                         <at name="name">border</at>
                        </super>
                       </object>
                      </at>
                     </item>
                    </object>
                   </at>
                  </object>
                 </at>
                 <at name="actionCommand">del</at>
                 <at name="name">deleteFormButton</at>
                 <at name="width">75</at>
                 <at name="text">del</at>
                 <at name="toolTipText">Delete current tab from the section.</at>
                 <at name="height">29</at>
                </object>
               </at>
              </object>
             </at>
            </object>
           </at>
          </item>
         </object>
        </at>
        <at name="properties">
         <object classname="com.jeta.forms.store.memento.PropertiesMemento">
          <at name="classname">com.jeta.forms.gui.form.GridView</at>
          <at name="properties">
           <object classname="com.jeta.forms.store.support.PropertyMap">
            <at name="border">
             <object classname="com.jeta.forms.store.properties.CompoundBorderProperty">
              <super classname="com.jeta.forms.store.properties.BorderProperty">
               <at name="name">border</at>
              </super>
              <at name="borders">
               <object classname="java.util.LinkedList"/>
              </at>
             </object>
            </at>
            <at name="name"/>
            <at name="fill">
             <object classname="com.jeta.forms.store.properties.effects.PaintProperty">
              <at name="name">fill</at>
             </object>
            </at>
            <at name="scollBars">
             <object classname="com.jeta.forms.store.properties.ScrollBarsProperty">
              <at name="name">scollBars</at>
              <at name="verticalpolicy">21</at>
              <at name="horizontalpolicy">31</at>
              <at name="border">
               <object classname="com.jeta.forms.store.properties.CompoundBorderProperty">
                <super classname="com.jeta.forms.store.properties.BorderProperty">
                 <at name="name">border</at>
                </super>
                <at name="borders">
                 <object classname="java.util.LinkedList">
                  <item >
                   <at name="value">
                    <object classname="com.jeta.forms.store.properties.DefaultBorderProperty">
                     <super classname="com.jeta.forms.store.properties.BorderProperty">
                      <at name="name">border</at>
                     </super>
                    </object>
                   </at>
                  </item>
                 </object>
                </at>
               </object>
              </at>
             </object>
            </at>
           </object>
          </at>
         </object>
        </at>
        <at name="cellpainters">
         <object classname="com.jeta.forms.store.support.Matrix">
          <at name="rows">
           <object classname="[Ljava.lang.Object;" size="7">
            <at name="item" index="0">
             <object classname="[Ljava.lang.Object;" size="2"/>
            </at>
            <at name="item" index="1">
             <object classname="[Ljava.lang.Object;" size="2"/>
            </at>
            <at name="item" index="2">
             <object classname="[Ljava.lang.Object;" size="2"/>
            </at>
            <at name="item" index="3">
             <object classname="[Ljava.lang.Object;" size="2"/>
            </at>
            <at name="item" index="4">
             <object classname="[Ljava.lang.Object;" size="2"/>
            </at>
            <at name="item" index="5">
             <object classname="[Ljava.lang.Object;" size="2"/>
            </at>
            <at name="item" index="6">
             <object classname="[Ljava.lang.Object;" size="2"/>
            </at>
           </object>
          </at>
         </object>
        </at>
        <at name="rowgroups">
         <object classname="com.jeta.forms.store.memento.FormGroupSet">
          <at name="groups">
           <object classname="java.util.HashMap"/>
          </at>
         </object>
        </at>
        <at name="colgroups">
         <object classname="com.jeta.forms.store.memento.FormGroupSet">
          <at name="groups">
           <object classname="java.util.HashMap"/>
          </at>
         </object>
        </at>
       </object>
      </at>
     </item>
    </object>
   </at>
   <at name="properties">
    <object classname="com.jeta.forms.store.memento.PropertiesMemento">
     <at name="classname">com.jeta.forms.gui.form.GridView</at>
     <at name="properties">
      <object classname="com.jeta.forms.store.support.PropertyMap">
       <at name="border">
        <object classname="com.jeta.forms.store.properties.CompoundBorderProperty">
         <super classname="com.jeta.forms.store.properties.BorderProperty">
          <at name="name">border</at>
         </super>
         <at name="borders">
          <object classname="java.util.LinkedList"/>
         </at>
        </object>
       </at>
       <at name="name"/>
       <at name="fill">
        <object classname="com.jeta.forms.store.properties.effects.PaintProperty">
         <at name="name">fill</at>
        </object>
       </at>
       <at name="scollBars">
        <object classname="com.jeta.forms.store.properties.ScrollBarsProperty">
         <at name="name">scollBars</at>
         <at name="verticalpolicy">21</at>
         <at name="horizontalpolicy">31</at>
         <at name="border">
          <object classname="com.jeta.forms.store.properties.CompoundBorderProperty">
           <super classname="com.jeta.forms.store.properties.BorderProperty">
            <at name="name">border</at>
           </super>
           <at name="borders">
            <object classname="java.util.LinkedList">
             <item >
              <at name="value">
               <object classname="com.jeta.forms.store.properties.DefaultBorderProperty">
                <super classname="com.jeta.forms.store.properties.BorderProperty">
                 <at name="name">border</at>
                </super>
               </object>
              </at>
             </item>
            </object>
           </at>
          </object>
         </at>
        </object>
       </at>
      </object>
     </at>
    </object>
   </at>
   <at name="cellpainters">
    <object classname="com.jeta.forms.store.support.Matrix">
     <at name="rows">
      <object classname="[Ljava.lang.Object;" size="22">
       <at name="item" index="0">
        <object classname="[Ljava.lang.Object;" size="20"/>
       </at>
       <at name="item" index="1">
        <object classname="[Ljava.lang.Object;" size="20"/>
       </at>
       <at name="item" index="2">
        <object classname="[Ljava.lang.Object;" size="20"/>
       </at>
       <at name="item" index="3">
        <object classname="[Ljava.lang.Object;" size="20"/>
       </at>
       <at name="item" index="4">
        <object classname="[Ljava.lang.Object;" size="20"/>
       </at>
       <at name="item" index="5">
        <object classname="[Ljava.lang.Object;" size="20"/>
       </at>
       <at name="item" index="6">
        <object classname="[Ljava.lang.Object;" size="20"/>
       </at>
       <at name="item" index="7">
        <object classname="[Ljava.lang.Object;" size="20"/>
       </at>
       <at name="item" index="8">
        <object classname="[Ljava.lang.Object;" size="20"/>
       </at>
       <at name="item" index="9">
        <object classname="[Ljava.lang.Object;" size="20"/>
       </at>
       <at name="item" index="10">
        <object classname="[Ljava.lang.Object;" size="20"/>
       </at>
       <at name="item" index="11">
        <object classname="[Ljava.lang.Object;" size="20"/>
       </at>
       <at name="item" index="12">
        <object classname="[Ljava.lang.Object;" size="20"/>
       </at>
       <at name="item" index="13">
        <object classname="[Ljava.lang.Object;" size="20"/>
       </at>
       <at name="item" index="14">
        <object classname="[Ljava.lang.Object;" size="20"/>
       </at>
       <at name="item" index="15">
        <object classname="[Ljava.lang.Object;" size="20"/>
       </at>
       <at name="item" index="16">
        <object classname="[Ljava.lang.Object;" size="20"/>
       </at>
       <at name="item" index="17">
        <object classname="[Ljava.lang.Object;" size="20"/>
       </at>
       <at name="item" index="18">
        <object classname="[Ljava.lang.Object;" size="20"/>
       </at>
       <at name="item" index="19">
        <object classname="[Ljava.lang.Object;" size="20"/>
       </at>
       <at name="item" index="20">
        <object classname="[Ljava.lang.Object;" size="20"/>
       </at>
       <at name="item" index="21">
        <object classname="[Ljava.lang.Object;" size="20"/>
       </at>
      </object>
     </at>
    </object>
   </at>
   <at name="rowgroups">
    <object classname="com.jeta.forms.store.memento.FormGroupSet">
     <at name="groups">
      <object classname="java.util.HashMap"/>
     </at>
    </object>
   </at>
   <at name="colgroups">
    <object classname="com.jeta.forms.store.memento.FormGroupSet">
     <at name="groups">
      <object classname="java.util.HashMap"/>
     </at>
    </object>
   </at>
  </object>
 </at>
</object>
